{"textPanel":{"list":[{"title":"目的","data":null},{"title":"原理","data":null},{"title":"步骤","data":null},{"title":"结论","data":null},{"title":"器材","data":null}],"x":0,"y":0,"width":600,"height":600},"chemData":{"id":"","dataVersion":2,"moduleType":21,"moduleData":{"viewPort":{"x":415.81560348456526,"y":452.365302160242,"scaleX":1,"scaleY":1},"configData":{"backgroundColor":3422529,"equTypeIsArrow":false,"scientific":false,"equDefaultStatus":true},"moduleConfigData":{"showElectrons":true},"eqs":[{"dataId":"RubberPlug","className":"RubberPlug","UID":22,"x":1605.4710510236373,"y":574.272799009509,"rotation":0,"insIdx":3,"attrMode":2,"showEquation":true,"bindBottleUID":21,"scale":1},{"dataId":"NarrowMouthBottle","className":"NarrowMouthBottle","UID":21,"x":1607.4710510236373,"y":699.2727990095091,"rotation":0,"insIdx":2,"attrMode":2,"showEquation":true,"sampleData":{"pDataId":"NaOH_aq","conc":0.1,"concIdx":0},"bottleHeadBgType":1},{"dataId":"Galvanometer","className":"Galvanometer","UID":234,"x":909.3111704093099,"y":4.321265302889344,"rotation":0,"insIdx":1,"attrMode":0,"showEquation":true},{"dataId":"FlexibleGlassCatheter","className":"FlexibleGlassCatheter","UID":233,"x":1364.011874586476,"y":269.17945092177956,"rotation":0,"insIdx":1,"showEquation":true,"curLength":375.5829445812616,"angle":0},{"dataId":"FlexibleGlassCatheter","className":"FlexibleGlassCatheter","UID":25,"x":815.5118745864761,"y":269.1794509217796,"rotation":0,"insIdx":2,"showEquation":true,"curLength":365.82559260716096,"angle":-3.141592653589793},{"dataId":"ElectrodeC","className":"ElectrodeC","UID":229,"x":1390.011874586476,"y":574.1794509217796,"rotation":0,"insIdx":1,"showEquation":true,"showPolarity":true},{"dataId":"ElectrodeC","className":"ElectrodeC","UID":230,"x":790.0118745864761,"y":574.1794509217796,"rotation":0,"insIdx":2,"showEquation":true,"showPolarity":true},{"dataId":"RubberPlug","className":"RubberPlug","UID":225,"x":1264.011874586476,"y":849.1794509217796,"rotation":3.141592653589793,"insIdx":1,"attrMode":0,"showEquation":true,"scale":0.35},{"dataId":"RubberPlug","className":"RubberPlug","UID":226,"x":915.5118745864761,"y":849.1794509217796,"rotation":3.141592653589793,"insIdx":2,"attrMode":0,"showEquation":true,"scale":0.35},{"dataId":"SingleSwitch","className":"SingleSwitch","UID":236,"x":1234.550111880146,"y":56.338319097355566,"rotation":0,"insIdx":1,"attrMode":0,"showEquation":true,"knifeRotation":-0.6846072080498555},{"dataId":"O2_Bag","className":"GasBag","UID":231,"x":1809.253265655659,"y":259.6777305837842,"rotation":0,"insIdx":1,"showEquation":true,"valuePercent":1,"gasType":"O2","flipped":true,"label":"O₂"},{"dataId":"H2_Bag","className":"GasBag","UID":23,"x":374.6113218218894,"y":261.3413518973553,"rotation":0,"insIdx":1,"showEquation":true,"valuePercent":1,"gasType":"H2","flipped":false,"label":"H₂"},{"dataId":"TwoCellElectrolyzerCombEq","className":"TwoCellElectrolyzer","UID":224,"x":1090.011874586476,"y":619.1794509217796,"rotation":0,"insIdx":1,"showEquation":true,"showEleAni":true,"chemicalDataAry":[{"phases":[{"phaseType":"g","temperature":300,"chemicals":[{"formula":"O2","valence":0,"mol":0.002108764376739052},{"formula":"N2","valence":0,"mol":0.00002460196033773638},{"formula":"H2","valence":0,"mol":0.008346535673634898}]},{"phaseType":"l","temperature":300,"chemicals":[{"formula":"H2O","valence":0,"mol":74.25898148714305},{"formula":"Na","valence":1,"mol":0.13366608466263435},{"formula":"OH","valence":-1,"mol":0.13366608466276803},{"formula":"H","valence":1,"mol":1.3366624869099777e-13},{"formula":"O2","valence":0,"mol":1.7961391147202757e-13}]}]},{"phases":[{"phaseType":"g","temperature":300,"chemicals":[{"formula":"O2","valence":0,"mol":0.002108764376739052},{"formula":"N2","valence":0,"mol":0.00002460196033773638},{"formula":"H2","valence":0,"mol":0.008346535673634898}]},{"phaseType":"l","temperature":300,"chemicals":[{"formula":"H2O","valence":0,"mol":74.25898148714305},{"formula":"Na","valence":1,"mol":0.13366608466263435},{"formula":"OH","valence":-1,"mol":0.13366608466276803},{"formula":"H","valence":1,"mol":1.3366624869099777e-13},{"formula":"O2","valence":0,"mol":1.7961391147202757e-13}]}]}],"labels":[["",""],["",""]]},{"dataId":"RubberCatheter","className":"RubberCatheter","UID":232,"x":0,"y":0,"rotation":0,"insIdx":1,"attrMode":0,"showEquation":true,"curLength":0.001,"terminal0":{"x":1559.2532656556589,"y":269.6777305837842},"terminal1":{"x":1564.011874586476,"y":269.17945092177945}},{"dataId":"RedWire","className":"Wire","UID":235,"x":0,"y":0,"rotation":0,"insIdx":1,"attrMode":0,"showEquation":true,"terminal0":{"x":964.3111704093099,"y":70.32126530288934},"terminal1":{"x":1139.550111880146,"y":71.33831909735557},"skinType":0},{"dataId":"RedWire","className":"Wire","UID":237,"x":0,"y":0,"rotation":0,"insIdx":2,"attrMode":0,"showEquation":true,"terminal0":{"x":790.0118745864761,"y":346.67945092177956},"terminal1":{"x":854.3111704093097,"y":70.32126530288934},"skinType":0},{"dataId":"RedWire","className":"Wire","UID":238,"x":0,"y":0,"rotation":0,"insIdx":3,"attrMode":0,"showEquation":true,"terminal0":{"x":1333.550111880146,"y":71.33831909735557},"terminal1":{"x":1390.011874586476,"y":346.67945092177956},"skinType":0},{"dataId":"RubberCatheter","className":"RubberCatheter","UID":24,"x":0,"y":0,"rotation":0,"insIdx":2,"attrMode":0,"showEquation":true,"curLength":0.001,"terminal0":{"x":624.6113218218894,"y":271.3413518973552},"terminal1":{"x":615.511874586476,"y":269.1794509217795}}],"assembleData":[{"card":{"eqUID":22,"name":"plug"},"slot":{"eqUID":21,"name":"plug"}},{"card":{"eqUID":233,"name":"catheter"},"slot":{"eqUID":224,"name":"catheterR_0"}},{"card":{"eqUID":25,"name":"catheter"},"slot":{"eqUID":224,"name":"catheterL_1"}},{"card":{"eqUID":229,"name":"electrode"},"slot":{"eqUID":224,"name":"electrodeR"}},{"card":{"eqUID":230,"name":"electrode"},"slot":{"eqUID":224,"name":"electrodeL"}},{"card":{"eqUID":225,"name":"plug"},"slot":{"eqUID":224,"name":"plug_0"}},{"card":{"eqUID":226,"name":"plug"},"slot":{"eqUID":224,"name":"plug_1"}},{"card":{"eqUID":232,"name":"terminal0"},"slot":{"eqUID":231,"name":"rubber"}},{"card":{"eqUID":232,"name":"terminal1"},"slot":{"eqUID":233,"name":"rubber1"}},{"card":{"eqUID":235,"name":"terminal0"},"slot":{"eqUID":234,"name":"terminal1"}},{"card":{"eqUID":235,"name":"terminal1"},"slot":{"eqUID":236,"name":"terminal0"}},{"card":{"eqUID":237,"name":"terminal0"},"slot":{"eqUID":230,"name":"terminal"}},{"card":{"eqUID":237,"name":"terminal1"},"slot":{"eqUID":234,"name":"terminal0"}},{"card":{"eqUID":238,"name":"terminal0"},"slot":{"eqUID":236,"name":"terminal1"}},{"card":{"eqUID":238,"name":"terminal1"},"slot":{"eqUID":229,"name":"terminal"}},{"card":{"eqUID":24,"name":"terminal0"},"slot":{"eqUID":23,"name":"rubber"}},{"card":{"eqUID":24,"name":"terminal1"},"slot":{"eqUID":25,"name":"rubber1"}}],"targetIdData":[{"type":3,"card":{"eqUID":22,"name":"plug"},"slot":{"eqUID":21,"name":"plug"}}]},"moduleId":27}}