{"textPanel":{"list":[{"title":"目的","data":"<p>1、体验浓度、温度和催化剂对化学反应速率的影响</p>\n\n<p>2、理解改变反应条件可以调控化学反应的速率</p>\n"},{"title":"原理","data":"<p>1、Na₂S₂O₃+H₂SO₄=Na₂SO₄+SO₂&uarr;+S&darr;+</p>\n\n<p>H₂O</p>\n\n<p>2、2H₂O₂=2H₂O+O₂&uarr;</p>\n"},{"title":"用品","data":"<p>1、实验仪器：试管、量筒、胶头滴管、药匙、冰水浴、水浴锅</p>\n\n<p>2、实验药品：0.1mol/L Na₂S₂O₃溶液，0.1mol/L H₂SO₄溶液，10% H₂O₂溶液，1mol/L FeCl₃溶液，MnO₂粉末，蒸馏水</p>\n"},{"title":"步骤","data":"<p>1、浓度对化学反应速率的影响</p>\n\n<p>取两支大小相同的试管，分别加入2mL和1mL 0.1mol/L Na₂S₂O₃溶液，向盛有1 mL Na₂S₂O₃溶液的试管中加入1mL蒸馏水，摇匀。再同时向上述两支试管中加入2mL 0.1 mol/L H₂SO₄溶液，振荡。观察、比较两支试管中溶液出现浑浊的快慢。</p>\n\n<p>2、温度对化学反应速率的影响</p>\n\n<p>取两支大小相同的试管，各加入2mL 0.1mol/L Na₂S₂O₃溶液，分别放入盛有冷水和热水的两个烧杯中。再同时向上述两支试管中加入2mL 0.1mol/L H₂SO₄溶液，振荡。观察、比较两支试管中溶液出现浑浊的快慢。</p>\n\n<p>3、催化剂对化学反应速率的影响</p>\n\n<p>向三支大小相同的试管中各加入2mL 10%H₂O₂溶液，再向其中的两支试管中分别加入少量MnO₂粉末和2滴1mol/L FeCl₃溶液。观察、比较三支试管中气泡出现的快慢。</p>\n"},{"title":"结论","data":"<p>1、浓度越大，反应速率越快</p>\n\n<p>2、温度越高，反应速率越快</p>\n\n<p>3、催化剂可以加快反应速率，不同催化剂对反应速率的影响程度不同</p>\n"}],"x":0,"y":0,"width":600,"height":600},"chemData":{"chemBackGroundColor":3422529,"viewStack":{"x":252.5194080954534,"y":30.17136500357492,"scaleX":0.8110080000000003,"scaleY":0.8110080000000003},"magnifierData":[],"microAniData":{},"children":[{"breakImgAlpha":null,"x":810.3677037828083,"y":352.8866071689318,"rotation":0,"index":0,"name":"id_209_aq","uuid":"6054497608918397","addedNode":[],"currentPlugCurValue":null,"currentArea":null,"plugAnimation":false,"fun":false,"holdAnimation":false,"scaleX":1,"scaleY":1,"areaWasFullAry":[],"constructorAttribute":{"dataBuild":true},"medicineData":{"liquid":[{"dat":{"id":"1","name_cn":"蒸馏水","type_cn":"液体","chemical":"H2O","type":"Liquid","heat_vaporization":40800,"gas_heat_capacity":7,"heat_capacity":"4200","Available":"1","density_solid":0.917,"density_liquid":1,"density_gas":0.001,"molecular_mass":18,"melting_point":0,"boiling_point":100,"alpha_liquid":"0.2","color":"无色","solubility":0,"ksp":1e-14,"浓度1颜色":"无色","ions":[{"count":1,"name":"H","valence":1},{"count":1,"name":"OH","valence":-1}],"chemicalArr":["H2O"],"densityArr":[1]},"mol":55.55555555555556,"temp":25,"solvent":"H2O"},{"dat":{"id":"209","name_cn":"硫代硫酸钠溶液","type_cn":"固体","chemical":"Na2S2O3","type":"p","heat_vaporization":40800,"gas_heat_capacity":7,"heat_capacity":"4200","Available":"1","density_solid":1.667,"density_liquid":1.667,"molecular_mass":158.2,"melting_point":48.3,"color":"0xffffff","solubility":73,"ions":[{"count":2,"name":"Na","valence":1},{"count":1,"name":"S2O3","valence":-2}],"sol_curve":"70.26852528437541+(0.13082522366070748*x)+(0.0015095357142860255*Math.pow(x,2))","chemicalArr":["Na2S2O3"],"densityArr":[1]},"mol":0.10011111111111111,"temp":25,"solvent":"H2O"}],"solid":{},"gas":[{"dat":{"id":"133","name_cn":"氧气","chemical":"O2","type":"Gas","heat_vaporization":40800,"gas_heat_capacity":7,"Available":"1","density_solid":2,"density_liquid":1,"density_gas":0.001429,"molecular_mass":32,"melting_point":-218.79,"boiling_point":-182.95,"color":"无色","数据来源或溶解气体的体积":"0.03体积","solubility":0.00434,"浓度1颜色":"0xFFFFFF"},"mol":0.002483118860249574,"temp":25},{"dat":{"id":"111","name_cn":"氮气","type_cn":"气体","chemical":"N2","type":"Gas","heat_vaporization":40800,"gas_heat_capacity":7,"Available":"1","density_solid":2,"density_liquid":1,"density_gas":0.001251,"molecular_mass":28,"melting_point":-210,"boiling_point":-195.8,"color":"无色","数据来源或溶解气体的体积":"0","solubility":0,"浓度1颜色":"0xFFFFFF"},"mol":0.009932475440998297,"temp":25}],"temp":25,"ion":[{"dat":{"count":2,"name":"Na","valence":1},"mol":1.1431993292118627},{"dat":{"count":1,"name":"S2O3","valence":-2},"mol":0.5715996646059314}],"dissolve":[],"ionMedicine":[{"dat":{"id":"209","name_cn":"硫代硫酸钠溶液","type_cn":"固体","chemical":"Na2S2O3","type":"p","heat_vaporization":40800,"gas_heat_capacity":7,"heat_capacity":"4200","Available":"1","density_solid":1.667,"density_liquid":1.667,"molecular_mass":158.2,"melting_point":48.3,"color":"0xffffff","solubility":73,"ions":[{"count":2,"name":"Na","valence":1},{"count":1,"name":"S2O3","valence":-2}],"sol_curve":"70.26852528437541+(0.13082522366070748*x)+(0.0015095357142860255*Math.pow(x,2))","chemicalArr":["Na2S2O3"],"densityArr":[1]},"mol":0.2355587616158266},{"dat":{"id":"209","name_cn":"硫代硫酸钠溶液","type_cn":"固体","chemical":"Na2S2O3","type":"p","heat_vaporization":40800,"gas_heat_capacity":7,"heat_capacity":"4200","Available":"1","density_solid":1.667,"density_liquid":1.667,"molecular_mass":158.2,"melting_point":48.3,"color":"0xffffff","solubility":73,"ions":[{"count":2,"name":"Na","valence":1},{"count":1,"name":"S2O3","valence":-2}],"sol_curve":"70.26852528437541+(0.13082522366070748*x)+(0.0015095357142860255*Math.pow(x,2))","chemicalArr":["Na2S2O3"],"densityArr":[1]},"mol":0.2355587616158266},{"dat":{"id":"209","name_cn":"硫代硫酸钠溶液","type_cn":"固体","chemical":"Na2S2O3","type":"p","heat_vaporization":40800,"gas_heat_capacity":7,"heat_capacity":"4200","Available":"1","density_solid":1.667,"density_liquid":1.667,"molecular_mass":158.2,"melting_point":48.3,"color":"0xffffff","solubility":73,"ions":[{"count":2,"name":"Na","valence":1},{"count":1,"name":"S2O3","valence":-2}],"sol_curve":"70.26852528437541+(0.13082522366070748*x)+(0.0015095357142860255*Math.pow(x,2))","chemicalArr":["Na2S2O3"],"densityArr":[1]},"mol":0.2356680599216428},{"dat":{"id":"209","name_cn":"硫代硫酸钠溶液","type_cn":"固体","chemical":"Na2S2O3","type":"p","heat_vaporization":40800,"gas_heat_capacity":7,"heat_capacity":"4200","Available":"1","density_solid":1.667,"density_liquid":1.667,"molecular_mass":158.2,"melting_point":48.3,"color":"0xffffff","solubility":73,"ions":[{"count":2,"name":"Na","valence":1},{"count":1,"name":"S2O3","valence":-2}],"sol_curve":"70.26852528437541+(0.13082522366070748*x)+(0.0015095357142860255*Math.pow(x,2))","chemicalArr":["Na2S2O3"],"densityArr":[1]},"mol":0.2358204935731775},{"dat":{"id":"209","name_cn":"硫代硫酸钠溶液","type_cn":"固体","chemical":"Na2S2O3","type":"p","heat_vaporization":40800,"gas_heat_capacity":7,"heat_capacity":"4200","Available":"1","density_solid":1.667,"density_liquid":1.667,"molecular_mass":158.2,"melting_point":48.3,"color":"0xffffff","solubility":73,"ions":[{"count":2,"name":"Na","valence":1},{"count":1,"name":"S2O3","valence":-2}],"sol_curve":"70.26852528437541+(0.13082522366070748*x)+(0.0015095357142860255*Math.pow(x,2))","chemicalArr":["Na2S2O3"],"densityArr":[1]},"mol":0.10011111111111111}]},"bringToFront":true,"instanceName":"main.liquid.Na2S2O3_aq^1","dataVersion":7,"plugAnimationOpen":true,"canCheckPure":true,"hasCovered":true,"labelType":0,"specialLabel":null,"liquidActiveCount":0,"children":[]},{"breakImgAlpha":0,"labelTop":"","labelBottom":"","x":1730.1942116901764,"y":1093.8350837426328,"rotation":0,"index":1,"name":"BigTestTube","limitDragData":{},"uuid":"09866629428699314","addedNode":[],"currentPlugCurValue":null,"currentArea":null,"plugAnimation":false,"fun":false,"holdAnimation":false,"scaleX":1,"scaleY":1,"areaWasFullAry":[],"constructorAttribute":{"dataBuild":true},"medicineData":{"liquid":[],"solid":{},"gas":[{"dat":{"id":"133","name_cn":"氧气","chemical":"O2","type":"Gas","heat_vaporization":40800,"gas_heat_capacity":7,"Available":"1","density_solid":2,"density_liquid":1,"density_gas":0.001429,"molecular_mass":32,"melting_point":-218.79,"boiling_point":-182.95,"color":"无色","数据来源或溶解气体的体积":"0.03体积","solubility":0.00434,"浓度1颜色":"0xFFFFFF"},"mol":0.00040876318889103327,"temp":25},{"dat":{"id":"111","name_cn":"氮气","type_cn":"气体","chemical":"N2","type":"Gas","heat_vaporization":40800,"gas_heat_capacity":7,"Available":"1","density_solid":2,"density_liquid":1,"density_gas":0.001251,"molecular_mass":28,"melting_point":-210,"boiling_point":-195.8,"color":"无色","数据来源或溶解气体的体积":"0","solubility":0,"浓度1颜色":"0xFFFFFF"},"mol":0.001635052755564133,"temp":25}],"temp":25,"ion":[],"dissolve":[],"ionMedicine":[]},"bringToFront":true,"instanceName":"main.reactor.BigTestTube^1","dataVersion":7,"plugAnimationOpen":true,"canCheckPure":true,"children":[]},{"breakImgAlpha":0,"addTwoContainerCollision":true,"labelTop":"","labelBottom":"","x":1891.5984520054535,"y":1096.5830288634581,"rotation":0,"index":2,"name":"BigTestTube","limitDragData":{},"uuid":"42950629988938127","addedNode":[],"currentPlugCurValue":null,"currentArea":null,"plugAnimation":false,"fun":false,"holdAnimation":false,"scaleX":1,"scaleY":1,"areaWasFullAry":[],"constructorAttribute":{"dataBuild":true},"medicineData":{"liquid":[],"solid":{},"gas":[{"dat":{"id":"133","name_cn":"氧气","chemical":"O2","type":"Gas","heat_vaporization":40800,"gas_heat_capacity":7,"Available":"1","density_solid":2,"density_liquid":1,"density_gas":0.001429,"molecular_mass":32,"melting_point":-218.79,"boiling_point":-182.95,"color":"无色","数据来源或溶解气体的体积":"0.03体积","solubility":0.00434,"浓度1颜色":"0xFFFFFF"},"mol":0.00040876318889103327,"temp":25},{"dat":{"id":"111","name_cn":"氮气","type_cn":"气体","chemical":"N2","type":"Gas","heat_vaporization":40800,"gas_heat_capacity":7,"Available":"1","density_solid":2,"density_liquid":1,"density_gas":0.001251,"molecular_mass":28,"melting_point":-210,"boiling_point":-195.8,"color":"无色","数据来源或溶解气体的体积":"0","solubility":0,"浓度1颜色":"0xFFFFFF"},"mol":0.001635052755564133,"temp":25}],"temp":25,"ion":[],"dissolve":[],"ionMedicine":[]},"bringToFront":true,"instanceName":"main.reactor.BigTestTube^2","dataVersion":7,"plugAnimationOpen":true,"canCheckPure":true,"children":[]},{"breakImgAlpha":null,"x":1612.1676557213716,"y":441.0184167127259,"rotation":0,"index":3,"name":"id_210_aq","uuid":"41082276292896003","addedNode":[],"currentPlugCurValue":null,"currentArea":null,"plugAnimation":false,"fun":false,"holdAnimation":false,"scaleX":1,"scaleY":1,"areaWasFullAry":[],"constructorAttribute":{"dataBuild":true},"medicineData":{"liquid":[{"dat":{"id":"1","name_cn":"蒸馏水","type_cn":"液体","chemical":"H2O","type":"Liquid","heat_vaporization":40800,"gas_heat_capacity":7,"heat_capacity":"4200","Available":"1","density_solid":0.917,"density_liquid":1,"density_gas":0.001,"molecular_mass":18,"melting_point":0,"boiling_point":100,"alpha_liquid":"0.2","color":"无色","solubility":0,"ksp":1e-14,"浓度1颜色":"无色","ions":[{"count":1,"name":"H","valence":1},{"count":1,"name":"OH","valence":-1}],"chemicalArr":["H2O"],"densityArr":[1]},"mol":38.87936243528816,"temp":25,"solvent":"H2O"},{"dat":{"id":"72","name_cn":"过氧化氢","type_cn":"液体","chemical":"H2O2","type":"Liquid","heat_vaporization":40800,"gas_heat_capacity":7,"heat_capacity":"4200","Available":"0","density_solid":1.71,"density_liquid":1.463,"density_gas":0.001,"molecular_mass":34,"melting_point":-0.43,"boiling_point":150.2,"color":"无色","solubility":9999,"浓度1颜色":"0xFFFFFF"},"mol":12.916202047915341,"temp":25,"solvent":"H2O"}],"solid":{},"gas":[{"dat":{"id":"133","name_cn":"氧气","chemical":"O2","type":"Gas","heat_vaporization":40800,"gas_heat_capacity":7,"Available":"1","density_solid":2,"density_liquid":1,"density_gas":0.001429,"molecular_mass":32,"melting_point":-218.79,"boiling_point":-182.95,"color":"无色","数据来源或溶解气体的体积":"0.03体积","solubility":0.00434,"浓度1颜色":"0xFFFFFF"},"mol":0.00117350579930152,"temp":25},{"dat":{"id":"111","name_cn":"氮气","type_cn":"气体","chemical":"N2","type":"Gas","heat_vaporization":40800,"gas_heat_capacity":7,"Available":"1","density_solid":2,"density_liquid":1,"density_gas":0.001251,"molecular_mass":28,"melting_point":-210,"boiling_point":-195.8,"color":"无色","数据来源或溶解气体的体积":"0","solubility":0,"浓度1颜色":"0xFFFFFF"},"mol":0.00469402319720608,"temp":25}],"temp":25,"ion":[],"dissolve":[],"ionMedicine":[]},"bringToFront":true,"instanceName":"main.liquid.H2O2%30&H2O%70^1","dataVersion":7,"plugAnimationOpen":true,"canCheckPure":true,"hasCovered":true,"labelType":0,"specialLabel":null,"liquidActiveCount":0,"children":[{"breakImgAlpha":null,"x":64.5,"y":-110,"rotation":0,"index":0,"name":"AcidBrownDropper","uuid":"9498848877630359","addedNode":[],"currentPlugCurValue":null,"currentArea":null,"plugAnimation":false,"fun":false,"holdAnimation":false,"scaleX":1,"scaleY":1,"areaWasFullAry":[],"addedBottle":"41082276292896003","constructorAttribute":{"dataBuild":true},"medicineData":{"liquid":[{"dat":{"id":"1","name_cn":"蒸馏水","type_cn":"液体","chemical":"H2O","type":"Liquid","heat_vaporization":40800,"gas_heat_capacity":7,"heat_capacity":"4200","Available":"1","density_solid":0.917,"density_liquid":1,"density_gas":0.001,"molecular_mass":18,"melting_point":0,"boiling_point":100,"alpha_liquid":"0.2","color":"无色","solubility":0,"ksp":1e-14,"浓度1颜色":"无色","ions":[{"count":1,"name":"H","valence":1},{"count":1,"name":"OH","valence":-1}],"chemicalArr":["H2O"],"densityArr":[1]},"mol":0.09368099259866004,"temp":25,"solvent":"H2O"},{"dat":{"id":"72","name_cn":"过氧化氢","type_cn":"液体","chemical":"H2O2","type":"Liquid","heat_vaporization":40800,"gas_heat_capacity":7,"heat_capacity":"4200","Available":"0","density_solid":1.71,"density_liquid":1.463,"density_gas":0.001,"molecular_mass":34,"melting_point":-0.43,"boiling_point":150.2,"color":"无色","solubility":9999,"浓度1颜色":"0xFFFFFF"},"mol":0.031121977127776076,"temp":25,"solvent":"H2O"}],"solid":{},"gas":[{"dat":{"id":"133","name_cn":"氧气","chemical":"O2","type":"Gas","heat_vaporization":40800,"gas_heat_capacity":7,"Available":"1","density_solid":2,"density_liquid":1,"density_gas":0.001429,"molecular_mass":32,"melting_point":-218.79,"boiling_point":-182.95,"color":"无色","数据来源或溶解气体的体积":"0.03体积","solubility":0.00434,"浓度1颜色":"0xFFFFFF"},"mol":0.00019698543841526205,"temp":25},{"dat":{"id":"111","name_cn":"氮气","type_cn":"气体","chemical":"N2","type":"Gas","heat_vaporization":40800,"gas_heat_capacity":7,"Available":"1","density_solid":2,"density_liquid":1,"density_gas":0.001251,"molecular_mass":28,"melting_point":-210,"boiling_point":-195.8,"color":"无色","数据来源或溶解气体的体积":"0","solubility":0,"浓度1颜色":"0xFFFFFF"},"mol":0.0007879417536610482,"temp":25}],"temp":25,"ion":[{"dat":{"count":1,"name":"H","valence":1},"mol":1.688131486627854e-10},{"dat":{"count":1,"name":"OH","valence":-1},"mol":1.688131486627854e-10}],"dissolve":[],"ionMedicine":[{"dat":{"id":"1","name_cn":"蒸馏水","type_cn":"液体","chemical":"H2O","type":"Liquid","heat_vaporization":40800,"gas_heat_capacity":7,"heat_capacity":"4200","Available":"1","density_solid":0.917,"density_liquid":1,"density_gas":0.001,"molecular_mass":18,"melting_point":0,"boiling_point":100,"alpha_liquid":"0.2","color":"无色","solubility":0,"ksp":1e-14,"浓度1颜色":"无色","ions":[{"count":1,"name":"H","valence":1},{"count":1,"name":"OH","valence":-1}],"chemicalArr":["H2O"],"densityArr":[1]},"mol":1.688131486627854e-10}]},"bringToFront":true,"instanceName":"main.reactor.AcidBrownDropper^1","dataVersion":7,"plugAnimationOpen":true,"canCheckPure":true,"hasCovered":true,"currentCapacity":2.4095300625,"shouldAbsorb":false,"children":[]}]},{"breakImgAlpha":null,"x":1869.9614073440923,"y":357.51304971986553,"rotation":0,"index":4,"name":"id_64_aq","uuid":"6524985120820515","addedNode":[],"currentPlugCurValue":null,"currentArea":null,"plugAnimation":false,"fun":false,"holdAnimation":false,"scaleX":1,"scaleY":1,"areaWasFullAry":[],"constructorAttribute":{"dataBuild":true},"medicineData":{"liquid":[{"dat":{"id":"1","name_cn":"蒸馏水","type_cn":"液体","chemical":"H2O","type":"Liquid","heat_vaporization":40800,"gas_heat_capacity":7,"heat_capacity":"4200","Available":"1","density_solid":0.917,"density_liquid":1,"density_gas":0.001,"molecular_mass":18,"melting_point":0,"boiling_point":100,"alpha_liquid":"0.2","color":"无色","solubility":0,"ksp":1e-14,"浓度1颜色":"无色","ions":[{"count":1,"name":"H","valence":1},{"count":1,"name":"OH","valence":-1}],"chemicalArr":["H2O"],"densityArr":[1]},"mol":55.55555555555556,"temp":25,"solvent":"H2O"},{"dat":{"id":"64","name_cn":"氯化铁溶液","type_cn":"p","chemical":"FeCl3","type":"p","heat_vaporization":40800,"gas_heat_capacity":7,"Available":"1","density_solid":2.898,"density_liquid":1.82,"density_gas":0.0698,"molecular_mass":162.3,"melting_point":306,"boiling_point":315,"color":"0x884705","solubility":91.8,"浓度1颜色":"0xEBE83B","ions":[{"count":1,"name":"Fe","valence":3},{"count":3,"name":"Cl","valence":-1}],"chemicalArr":["FeCl3"],"densityArr":[1]},"mol":1.4164919852034525,"temp":25,"solvent":"H2O"}],"solid":{},"gas":[{"dat":{"id":"133","name_cn":"氧气","chemical":"O2","type":"Gas","heat_vaporization":40800,"gas_heat_capacity":7,"Available":"1","density_solid":2,"density_liquid":1,"density_gas":0.001429,"molecular_mass":32,"melting_point":-218.79,"boiling_point":-182.95,"color":"无色","数据来源或溶解气体的体积":"0.03体积","solubility":0.00434,"浓度1颜色":"0xFFFFFF"},"mol":0.002483118860249574,"temp":25},{"dat":{"id":"111","name_cn":"氮气","type_cn":"气体","chemical":"N2","type":"Gas","heat_vaporization":40800,"gas_heat_capacity":7,"Available":"1","density_solid":2,"density_liquid":1,"density_gas":0.001251,"molecular_mass":28,"melting_point":-210,"boiling_point":-195.8,"color":"无色","数据来源或溶解气体的体积":"0","solubility":0,"浓度1颜色":"0xFFFFFF"},"mol":0.009932475440998297,"temp":25}],"temp":25,"ion":[{"dat":{"count":1,"name":"Fe","valence":3},"mol":1.9829142269761209},{"dat":{"count":3,"name":"Cl","valence":-1},"mol":5.948742680928364}],"dissolve":[],"ionMedicine":[{"dat":{"id":"64","name_cn":"氯化铁溶液","type_cn":"p","chemical":"FeCl3","type":"p","heat_vaporization":40800,"gas_heat_capacity":7,"Available":"1","density_solid":2.898,"density_liquid":1.82,"density_gas":0.0698,"molecular_mass":162.3,"melting_point":306,"boiling_point":315,"color":"0x884705","solubility":91.8,"浓度1颜色":"0xEBE83B","ions":[{"count":1,"name":"Fe","valence":3},{"count":3,"name":"Cl","valence":-1}],"chemicalArr":["FeCl3"],"densityArr":[1]},"mol":0.2829839704069051},{"dat":{"id":"64","name_cn":"氯化铁溶液","type_cn":"p","chemical":"FeCl3","type":"p","heat_vaporization":40800,"gas_heat_capacity":7,"Available":"1","density_solid":2.898,"density_liquid":1.82,"density_gas":0.0698,"molecular_mass":162.3,"melting_point":306,"boiling_point":315,"color":"0x884705","solubility":91.8,"浓度1颜色":"0xEBE83B","ions":[{"count":1,"name":"Fe","valence":3},{"count":3,"name":"Cl","valence":-1}],"chemicalArr":["FeCl3"],"densityArr":[1]},"mol":0.2829839704069051},{"dat":{"id":"64","name_cn":"氯化铁溶液","type_cn":"p","chemical":"FeCl3","type":"p","heat_vaporization":40800,"gas_heat_capacity":7,"Available":"1","density_solid":2.898,"density_liquid":1.82,"density_gas":0.0698,"molecular_mass":162.3,"melting_point":306,"boiling_point":315,"color":"0x884705","solubility":91.8,"浓度1颜色":"0xEBE83B","ions":[{"count":1,"name":"Fe","valence":3},{"count":3,"name":"Cl","valence":-1}],"chemicalArr":["FeCl3"],"densityArr":[1]},"mol":0.28312384473197777},{"dat":{"id":"64","name_cn":"氯化铁溶液","type_cn":"p","chemical":"FeCl3","type":"p","heat_vaporization":40800,"gas_heat_capacity":7,"Available":"1","density_solid":2.898,"density_liquid":1.82,"density_gas":0.0698,"molecular_mass":162.3,"melting_point":306,"boiling_point":315,"color":"0x884705","solubility":91.8,"浓度1颜色":"0xEBE83B","ions":[{"count":1,"name":"Fe","valence":3},{"count":3,"name":"Cl","valence":-1}],"chemicalArr":["FeCl3"],"densityArr":[1]},"mol":0.28329839704069054},{"dat":{"id":"64","name_cn":"氯化铁溶液","type_cn":"p","chemical":"FeCl3","type":"p","heat_vaporization":40800,"gas_heat_capacity":7,"Available":"1","density_solid":2.898,"density_liquid":1.82,"density_gas":0.0698,"molecular_mass":162.3,"melting_point":306,"boiling_point":315,"color":"0x884705","solubility":91.8,"浓度1颜色":"0xEBE83B","ions":[{"count":1,"name":"Fe","valence":3},{"count":3,"name":"Cl","valence":-1}],"chemicalArr":["FeCl3"],"densityArr":[1]},"mol":1.4164919852034525}]},"bringToFront":true,"instanceName":"main.liquid.FeCl3_aq^1","dataVersion":7,"plugAnimationOpen":true,"canCheckPure":true,"hasCovered":true,"labelType":0,"specialLabel":null,"liquidActiveCount":0,"children":[]},{"breakImgAlpha":null,"x":555.904251763366,"y":348.6505167318643,"rotation":0,"index":5,"name":"id_1_aq","uuid":"2292091169162762","addedNode":[],"currentPlugCurValue":null,"currentArea":null,"plugAnimation":false,"fun":false,"holdAnimation":false,"scaleX":1,"scaleY":1,"areaWasFullAry":[],"constructorAttribute":{"dataBuild":true},"medicineData":{"liquid":[{"dat":{"id":"1","name_cn":"蒸馏水","type_cn":"液体","chemical":"H2O","type":"Liquid","heat_vaporization":40800,"gas_heat_capacity":7,"heat_capacity":"4200","Available":"1","density_solid":0.917,"density_liquid":1,"density_gas":0.001,"molecular_mass":18,"melting_point":0,"boiling_point":100,"alpha_liquid":"0.2","color":"无色","solubility":0,"ksp":1e-14,"浓度1颜色":"无色","ions":[{"count":1,"name":"H","valence":1},{"count":1,"name":"OH","valence":-1}],"chemicalArr":["H2O"],"densityArr":[1]},"mol":55.55555555555556,"temp":25,"solvent":"H2O"}],"solid":{},"gas":[{"dat":{"id":"133","name_cn":"氧气","chemical":"O2","type":"Gas","heat_vaporization":40800,"gas_heat_capacity":7,"Available":"1","density_solid":2,"density_liquid":1,"density_gas":0.001429,"molecular_mass":32,"melting_point":-218.79,"boiling_point":-182.95,"color":"无色","数据来源或溶解气体的体积":"0.03体积","solubility":0.00434,"浓度1颜色":"0xFFFFFF"},"mol":0.002483118860249574,"temp":25},{"dat":{"id":"111","name_cn":"氮气","type_cn":"气体","chemical":"N2","type":"Gas","heat_vaporization":40800,"gas_heat_capacity":7,"Available":"1","density_solid":2,"density_liquid":1,"density_gas":0.001251,"molecular_mass":28,"melting_point":-210,"boiling_point":-195.8,"color":"无色","数据来源或溶解气体的体积":"0","solubility":0,"浓度1颜色":"0xFFFFFF"},"mol":0.009932475440998297,"temp":25}],"temp":25,"ion":[],"dissolve":[],"ionMedicine":[]},"bringToFront":true,"instanceName":"main.liquid.H2O^1","dataVersion":7,"plugAnimationOpen":true,"canCheckPure":true,"hasCovered":true,"labelType":2,"specialLabel":null,"liquidActiveCount":0,"children":[]},{"breakImgAlpha":null,"x":1057.4832935642462,"y":345.8117048805173,"rotation":0,"index":6,"name":"id_153_aq","uuid":"22581978347496934","addedNode":[],"currentPlugCurValue":null,"currentArea":null,"plugAnimation":false,"fun":false,"holdAnimation":false,"scaleX":1,"scaleY":1,"areaWasFullAry":[],"constructorAttribute":{"dataBuild":true},"medicineData":{"liquid":[{"dat":{"id":"1","name_cn":"蒸馏水","type_cn":"液体","chemical":"H2O","type":"Liquid","heat_vaporization":40800,"gas_heat_capacity":7,"heat_capacity":"4200","Available":"1","density_solid":0.917,"density_liquid":1,"density_gas":0.001,"molecular_mass":18,"melting_point":0,"boiling_point":100,"alpha_liquid":"0.2","color":"无色","solubility":0,"ksp":1e-14,"浓度1颜色":"无色","ions":[{"count":1,"name":"H","valence":1},{"count":1,"name":"OH","valence":-1}],"chemicalArr":["H2O"],"densityArr":[1]},"mol":55.25903287598328,"temp":25,"solvent":"H2O"},{"dat":{"id":"76","name_cn":"硫酸","chemical":"H2SO4","type":"Liquid","heat_vaporization":40800,"gas_heat_capacity":7,"heat_capacity":"4200","Available":"1","density_solid":2,"density_liquid":1.84,"density_gas":0.001,"molecular_mass":98.1,"melting_point":10,"boiling_point":1000,"color":"无色","solubility":200,"浓度1颜色":"0xFFFFFF","solutionHeat":"60","ions":[{"count":2,"name":"H","valence":1},{"count":1,"name":"SO4","valence":-2}]},"mol":0.10011040925008974,"temp":25,"solvent":"H2O"}],"solid":{},"gas":[{"dat":{"id":"133","name_cn":"氧气","chemical":"O2","type":"Gas","heat_vaporization":40800,"gas_heat_capacity":7,"Available":"1","density_solid":2,"density_liquid":1,"density_gas":0.001429,"molecular_mass":32,"melting_point":-218.79,"boiling_point":-182.95,"color":"无色","数据来源或溶解气体的体积":"0.03体积","solubility":0.00434,"浓度1颜色":"0xFFFFFF"},"mol":0.002483118860249574,"temp":25},{"dat":{"id":"111","name_cn":"氮气","type_cn":"气体","chemical":"N2","type":"Gas","heat_vaporization":40800,"gas_heat_capacity":7,"Available":"1","density_solid":2,"density_liquid":1,"density_gas":0.001251,"molecular_mass":28,"melting_point":-210,"boiling_point":-195.8,"color":"无色","数据来源或溶解气体的体积":"0","solubility":0,"浓度1颜色":"0xFFFFFF"},"mol":0.009932475440998297,"temp":25}],"temp":25,"ion":[],"dissolve":[],"ionMedicine":[]},"bringToFront":true,"instanceName":"main.liquid.H2SO4_lx^1","dataVersion":7,"plugAnimationOpen":true,"canCheckPure":true,"hasCovered":true,"labelType":0,"specialLabel":null,"liquidActiveCount":0,"children":[]},{"breakImgAlpha":null,"x":1475.1407357230873,"y":544.4369585847171,"rotation":0,"index":7,"name":"id_110","uuid":"3374414839794362","addedNode":[],"currentPlugCurValue":null,"currentArea":null,"plugAnimation":false,"fun":false,"holdAnimation":false,"scaleX":1,"scaleY":1,"areaWasFullAry":[],"constructorAttribute":{"dataBuild":true},"medicineData":{"liquid":[],"solid":{"MnO2":{"dat":{"id":"110","name_cn":"二氧化锰","type_cn":"p","chemical":"MnO2","type":"p","heat_vaporization":40800,"gas_heat_capacity":7,"Available":"1","density_solid":5.026,"density_liquid":1,"density_gas":0.001,"molecular_mass":86.9,"melting_point":535,"boiling_point":99999,"color":"0x000000","solubility":0,"浓度1颜色":"0x000000","chemicalArr":["MnO2"],"densityArr":[1]},"mol":10.031991366759492}},"gas":[{"dat":{"id":"133","name_cn":"氧气","chemical":"O2","type":"Gas","heat_vaporization":40800,"gas_heat_capacity":7,"Available":"1","density_solid":2,"density_liquid":1,"density_gas":0.001429,"molecular_mass":32,"melting_point":-218.79,"boiling_point":-182.95,"color":"无色","数据来源或溶解气体的体积":"0.03体积","solubility":0.00434,"浓度1颜色":"0xFFFFFF"},"mol":0.0017725407538606288,"temp":25},{"dat":{"id":"111","name_cn":"氮气","type_cn":"气体","chemical":"N2","type":"Gas","heat_vaporization":40800,"gas_heat_capacity":7,"Available":"1","density_solid":2,"density_liquid":1,"density_gas":0.001251,"molecular_mass":28,"melting_point":-210,"boiling_point":-195.8,"color":"无色","数据来源或溶解气体的体积":"0","solubility":0,"浓度1颜色":"0xFFFFFF"},"mol":0.007090163015442515,"temp":25}],"temp":25,"ion":[],"dissolve":[],"ionMedicine":[]},"bringToFront":true,"instanceName":"main.solid.MnO2^1","dataVersion":7,"plugAnimationOpen":true,"canCheckPure":true,"noConfig":true,"children":[]},{"x":1340.7856260686851,"y":318.98379048455536,"rotation":0,"index":8,"name":"LabSpoon","uuid":"6038297364600693","addedNode":[],"currentPlugCurValue":null,"currentArea":null,"plugAnimation":false,"fun":false,"holdAnimation":false,"scaleX":1,"scaleY":1,"areaWasFullAry":[],"constructorAttribute":{"dataBuild":true},"medicineData":null,"bringToFront":true,"instanceName":"main.aid.LabSpoon^1","dataVersion":7,"canCheckPure":true,"_tempVo":[],"medicineAmount":0,"children":[]},{"breakImgAlpha":null,"x":2127.06809739344,"y":237.72904441281037,"rotation":0,"index":9,"name":"ADropper","uuid":"02329871477653378","addedNode":[],"currentPlugCurValue":null,"currentArea":null,"plugAnimation":false,"fun":false,"holdAnimation":false,"scaleX":1,"scaleY":1,"areaWasFullAry":[],"constructorAttribute":{"dataBuild":true},"medicineData":{"liquid":[],"solid":{},"gas":[{"dat":{"id":"133","name_cn":"氧气","chemical":"O2","type":"Gas","heat_vaporization":40800,"gas_heat_capacity":7,"Available":"1","density_solid":2,"density_liquid":1,"density_gas":0.001429,"molecular_mass":32,"melting_point":-218.79,"boiling_point":-182.95,"color":"无色","数据来源或溶解气体的体积":"0.03体积","solubility":0.00434,"浓度1颜色":"0xFFFFFF"},"mol":0.000008175263777820659,"temp":25},{"dat":{"id":"111","name_cn":"氮气","type_cn":"气体","chemical":"N2","type":"Gas","heat_vaporization":40800,"gas_heat_capacity":7,"Available":"1","density_solid":2,"density_liquid":1,"density_gas":0.001251,"molecular_mass":28,"melting_point":-210,"boiling_point":-195.8,"color":"无色","数据来源或溶解气体的体积":"0","solubility":0,"浓度1颜色":"0xFFFFFF"},"mol":0.000032701055111282634,"temp":25}],"temp":25,"ion":[],"dissolve":[],"ionMedicine":[]},"bringToFront":true,"instanceName":"main.aid.ADropper^1","dataVersion":7,"plugAnimationOpen":true,"canCheckPure":true,"hasCovered":true,"shouldAbsorb":false,"defaultColor":16777215,"defaultAlpha":0.2,"children":[]},{"breakImgAlpha":null,"x":2317.9133574237217,"y":237.72904441281037,"rotation":0,"index":10,"name":"ADropper","uuid":"6339639710082259","addedNode":[],"currentPlugCurValue":null,"currentArea":null,"plugAnimation":false,"fun":false,"holdAnimation":false,"scaleX":1,"scaleY":1,"areaWasFullAry":[],"constructorAttribute":{"dataBuild":true},"medicineData":{"liquid":[],"solid":{},"gas":[{"dat":{"id":"133","name_cn":"氧气","chemical":"O2","type":"Gas","heat_vaporization":40800,"gas_heat_capacity":7,"Available":"1","density_solid":2,"density_liquid":1,"density_gas":0.001429,"molecular_mass":32,"melting_point":-218.79,"boiling_point":-182.95,"color":"无色","数据来源或溶解气体的体积":"0.03体积","solubility":0.00434,"浓度1颜色":"0xFFFFFF"},"mol":0.000008175263777820659,"temp":25},{"dat":{"id":"111","name_cn":"氮气","type_cn":"气体","chemical":"N2","type":"Gas","heat_vaporization":40800,"gas_heat_capacity":7,"Available":"1","density_solid":2,"density_liquid":1,"density_gas":0.001251,"molecular_mass":28,"melting_point":-210,"boiling_point":-195.8,"color":"无色","数据来源或溶解气体的体积":"0","solubility":0,"浓度1颜色":"0xFFFFFF"},"mol":0.000032701055111282634,"temp":25}],"temp":25,"ion":[],"dissolve":[],"ionMedicine":[]},"bringToFront":true,"instanceName":"main.aid.ADropper^2","dataVersion":7,"plugAnimationOpen":true,"canCheckPure":true,"hasCovered":true,"shouldAbsorb":false,"defaultColor":16777215,"defaultAlpha":0.2,"children":[]},{"breakImgAlpha":null,"x":2517.9191666389174,"y":237.72904441281275,"rotation":0,"index":11,"name":"ADropper","uuid":"5852568384410011","addedNode":[],"currentPlugCurValue":null,"currentArea":null,"plugAnimation":false,"fun":false,"holdAnimation":false,"scaleX":1,"scaleY":1,"areaWasFullAry":[],"constructorAttribute":{"dataBuild":true},"medicineData":{"liquid":[],"solid":{},"gas":[{"dat":{"id":"133","name_cn":"氧气","chemical":"O2","type":"Gas","heat_vaporization":40800,"gas_heat_capacity":7,"Available":"1","density_solid":2,"density_liquid":1,"density_gas":0.001429,"molecular_mass":32,"melting_point":-218.79,"boiling_point":-182.95,"color":"无色","数据来源或溶解气体的体积":"0.03体积","solubility":0.00434,"浓度1颜色":"0xFFFFFF"},"mol":0.000008175263777820659,"temp":25},{"dat":{"id":"111","name_cn":"氮气","type_cn":"气体","chemical":"N2","type":"Gas","heat_vaporization":40800,"gas_heat_capacity":7,"Available":"1","density_solid":2,"density_liquid":1,"density_gas":0.001251,"molecular_mass":28,"melting_point":-210,"boiling_point":-195.8,"color":"无色","数据来源或溶解气体的体积":"0","solubility":0,"浓度1颜色":"0xFFFFFF"},"mol":0.000032701055111282634,"temp":25}],"temp":25,"ion":[],"dissolve":[],"ionMedicine":[]},"bringToFront":true,"instanceName":"main.aid.ADropper^3","dataVersion":7,"plugAnimationOpen":true,"canCheckPure":true,"hasCovered":true,"shouldAbsorb":false,"defaultColor":16777215,"defaultAlpha":0.2,"children":[]},{"breakImgAlpha":0,"labelTop":"","labelBottom":"","x":2256.9064751114342,"y":1095.872491889612,"rotation":0,"index":12,"name":"BigTestTube","limitDragData":{},"uuid":"568522769060541","addedNode":[],"currentPlugCurValue":null,"currentArea":null,"plugAnimation":false,"fun":false,"holdAnimation":false,"scaleX":1,"scaleY":1,"areaWasFullAry":[],"constructorAttribute":{"dataBuild":true},"medicineData":{"liquid":[],"solid":{},"gas":[{"dat":{"id":"133","name_cn":"氧气","chemical":"O2","type":"Gas","heat_vaporization":40800,"gas_heat_capacity":7,"Available":"1","density_solid":2,"density_liquid":1,"density_gas":0.001429,"molecular_mass":32,"melting_point":-218.79,"boiling_point":-182.95,"color":"无色","数据来源或溶解气体的体积":"0.03体积","solubility":0.00434,"浓度1颜色":"0xFFFFFF"},"mol":0.00040876318889103327,"temp":25},{"dat":{"id":"111","name_cn":"氮气","type_cn":"气体","chemical":"N2","type":"Gas","heat_vaporization":40800,"gas_heat_capacity":7,"Available":"1","density_solid":2,"density_liquid":1,"density_gas":0.001251,"molecular_mass":28,"melting_point":-210,"boiling_point":-195.8,"color":"无色","数据来源或溶解气体的体积":"0","solubility":0,"浓度1颜色":"0xFFFFFF"},"mol":0.001635052755564133,"temp":25}],"temp":25,"ion":[],"dissolve":[],"ionMedicine":[]},"bringToFront":true,"instanceName":"main.reactor.BigTestTube^3","dataVersion":7,"plugAnimationOpen":true,"canCheckPure":true,"children":[]},{"breakImgAlpha":0,"labelTop":"","labelBottom":"","x":2441.7617376709177,"y":1095.872568495465,"rotation":0,"index":13,"name":"BigTestTube","limitDragData":{},"uuid":"2869270569626925","addedNode":[],"currentPlugCurValue":null,"currentArea":null,"plugAnimation":false,"fun":false,"holdAnimation":false,"scaleX":1,"scaleY":1,"areaWasFullAry":[],"constructorAttribute":{"dataBuild":true},"medicineData":{"liquid":[],"solid":{},"gas":[{"dat":{"id":"133","name_cn":"氧气","chemical":"O2","type":"Gas","heat_vaporization":40800,"gas_heat_capacity":7,"Available":"1","density_solid":2,"density_liquid":1,"density_gas":0.001429,"molecular_mass":32,"melting_point":-218.79,"boiling_point":-182.95,"color":"无色","数据来源或溶解气体的体积":"0.03体积","solubility":0.00434,"浓度1颜色":"0xFFFFFF"},"mol":0.00040876318889103327,"temp":25},{"dat":{"id":"111","name_cn":"氮气","type_cn":"气体","chemical":"N2","type":"Gas","heat_vaporization":40800,"gas_heat_capacity":7,"Available":"1","density_solid":2,"density_liquid":1,"density_gas":0.001251,"molecular_mass":28,"melting_point":-210,"boiling_point":-195.8,"color":"无色","数据来源或溶解气体的体积":"0","solubility":0,"浓度1颜色":"0xFFFFFF"},"mol":0.001635052755564133,"temp":25}],"temp":25,"ion":[],"dissolve":[],"ionMedicine":[]},"bringToFront":true,"instanceName":"main.reactor.BigTestTube^4","dataVersion":7,"plugAnimationOpen":true,"canCheckPure":true,"children":[]},{"breakImgAlpha":0,"labelTop":"","labelBottom":"","x":2620.5895028085774,"y":1095.8724152837615,"rotation":0,"index":14,"name":"BigTestTube","limitDragData":{},"uuid":"9764831825720803","addedNode":[],"currentPlugCurValue":null,"currentArea":null,"plugAnimation":false,"fun":false,"holdAnimation":false,"scaleX":1,"scaleY":1,"areaWasFullAry":[],"constructorAttribute":{"dataBuild":true},"medicineData":{"liquid":[],"solid":{},"gas":[{"dat":{"id":"133","name_cn":"氧气","chemical":"O2","type":"Gas","heat_vaporization":40800,"gas_heat_capacity":7,"Available":"1","density_solid":2,"density_liquid":1,"density_gas":0.001429,"molecular_mass":32,"melting_point":-218.79,"boiling_point":-182.95,"color":"无色","数据来源或溶解气体的体积":"0.03体积","solubility":0.00434,"浓度1颜色":"0xFFFFFF"},"mol":0.00040876318889103327,"temp":25},{"dat":{"id":"111","name_cn":"氮气","type_cn":"气体","chemical":"N2","type":"Gas","heat_vaporization":40800,"gas_heat_capacity":7,"Available":"1","density_solid":2,"density_liquid":1,"density_gas":0.001251,"molecular_mass":28,"melting_point":-210,"boiling_point":-195.8,"color":"无色","数据来源或溶解气体的体积":"0","solubility":0,"浓度1颜色":"0xFFFFFF"},"mol":0.001635052755564133,"temp":25}],"temp":25,"ion":[],"dissolve":[],"ionMedicine":[]},"bringToFront":true,"instanceName":"main.reactor.BigTestTube^5","dataVersion":7,"plugAnimationOpen":true,"canCheckPure":true,"children":[]},{"breakImgAlpha":0,"addTwoContainerCollision":true,"labelTop":"","labelBottom":"","x":2058.775966508454,"y":1093.880624855408,"rotation":0,"index":15,"name":"BigTestTube","limitDragData":{},"uuid":"39737484846548643","addedNode":[],"currentPlugCurValue":null,"currentArea":null,"plugAnimation":false,"fun":false,"holdAnimation":false,"scaleX":1,"scaleY":1,"areaWasFullAry":[],"constructorAttribute":{"dataBuild":true},"lastRotation":0,"medicineData":{"liquid":[],"solid":{},"gas":[{"dat":{"id":"133","name_cn":"氧气","chemical":"O2","type":"Gas","heat_vaporization":40800,"gas_heat_capacity":7,"Available":"1","density_solid":2,"density_liquid":1,"density_gas":0.001429,"molecular_mass":32,"melting_point":-218.79,"boiling_point":-182.95,"color":"无色","数据来源或溶解气体的体积":"0.03体积","solubility":0.00434,"浓度1颜色":"0xFFFFFF"},"mol":0.00040876318889103327,"temp":25},{"dat":{"id":"111","name_cn":"氮气","type_cn":"气体","chemical":"N2","type":"Gas","heat_vaporization":40800,"gas_heat_capacity":7,"Available":"1","density_solid":2,"density_liquid":1,"density_gas":0.001251,"molecular_mass":28,"melting_point":-210,"boiling_point":-195.8,"color":"无色","数据来源或溶解气体的体积":"0","solubility":0,"浓度1颜色":"0xFFFFFF"},"mol":0.001635052755564133,"temp":25}],"temp":25,"ion":[],"dissolve":[],"ionMedicine":[]},"bringToFront":true,"instanceName":"main.reactor.BigTestTube^6","dataVersion":7,"plugAnimationOpen":true,"canCheckPure":true,"children":[]},{"breakImgAlpha":0,"labelTop":"","labelBottom":"","x":1528.3073610879692,"y":1093.691287675431,"rotation":0,"index":16,"name":"BigTestTube","limitDragData":{},"uuid":"07641928483731553","addedNode":[],"currentPlugCurValue":null,"currentArea":null,"plugAnimation":false,"fun":false,"holdAnimation":false,"scaleX":1,"scaleY":1,"areaWasFullAry":[],"constructorAttribute":{"dataBuild":true},"lastRotation":0,"medicineData":{"liquid":[],"solid":{},"gas":[{"dat":{"id":"133","name_cn":"氧气","chemical":"O2","type":"Gas","heat_vaporization":40800,"gas_heat_capacity":7,"Available":"1","density_solid":2,"density_liquid":1,"density_gas":0.001429,"molecular_mass":32,"melting_point":-218.79,"boiling_point":-182.95,"color":"无色","数据来源或溶解气体的体积":"0.03体积","solubility":0.00434,"浓度1颜色":"0xFFFFFF"},"mol":0.00040876318889103327,"temp":25},{"dat":{"id":"111","name_cn":"氮气","type_cn":"气体","chemical":"N2","type":"Gas","heat_vaporization":40800,"gas_heat_capacity":7,"Available":"1","density_solid":2,"density_liquid":1,"density_gas":0.001251,"molecular_mass":28,"melting_point":-210,"boiling_point":-195.8,"color":"无色","数据来源或溶解气体的体积":"0","solubility":0,"浓度1颜色":"0xFFFFFF"},"mol":0.001635052755564133,"temp":25}],"temp":25,"ion":[],"dissolve":[],"ionMedicine":[]},"bringToFront":true,"instanceName":"main.reactor.BigTestTube^7","dataVersion":7,"plugAnimationOpen":true,"canCheckPure":true,"children":[]},{"x":754.7068308698475,"y":1151.4276691397522,"rotation":0,"index":17,"name":"WaterBath","uuid":"29630353250134234","addedNode":[],"currentPlugCurValue":null,"currentContainer":"5588350734541694","currentArea":null,"plugAnimation":false,"fun":false,"holdAnimation":false,"scaleX":1,"scaleY":1,"areaWasFullAry":[],"constructorAttribute":{"dataBuild":true},"medicineData":null,"bringToFront":true,"instanceName":"main.aid.WaterBath^1","dataVersion":7,"canCheckPure":true,"openPowerSwitch":false,"waterTemp":25,"increaseType":0,"children":[{"breakImgAlpha":null,"labelTop":"","labelBottom":"","x":70,"y":-386,"rotation":0,"index":1,"name":"HugeBeaker","uuid":"5588350734541694","addedNode":[],"currentPlugCurValue":null,"currentArea":null,"plugAnimation":false,"fun":false,"holdAnimation":false,"scaleX":1,"scaleY":1,"areaWasFullAry":[],"currentHitObj":"29630353250134234","constructorAttribute":{"dataBuild":true},"lastRotation":0,"medicineData":{"liquid":[],"solid":{},"gas":[{"dat":{"id":"133","name_cn":"氧气","chemical":"O2","type":"Gas","heat_vaporization":40800,"gas_heat_capacity":7,"Available":"1","density_solid":2,"density_liquid":1,"density_gas":0.001429,"molecular_mass":32,"melting_point":-218.79,"boiling_point":-182.95,"color":"无色","数据来源或溶解气体的体积":"0.03体积","solubility":0.00434,"浓度1颜色":"0xFFFFFF"},"mol":0.011445369288948902,"temp":25.000000000000004},{"dat":{"id":"111","name_cn":"氮气","type_cn":"气体","chemical":"N2","type":"Gas","heat_vaporization":40800,"gas_heat_capacity":7,"Available":"1","density_solid":2,"density_liquid":1,"density_gas":0.001251,"molecular_mass":28,"melting_point":-210,"boiling_point":-195.8,"color":"无色","数据来源或溶解气体的体积":"0","solubility":0,"浓度1颜色":"0xFFFFFF"},"mol":0.04578147715579561,"temp":25.000000000000004}],"temp":25,"ion":[],"dissolve":[],"ionMedicine":[]},"bringToFront":true,"instanceName":"main.reactor.HugeBeaker^1","dataVersion":7,"plugAnimationOpen":true,"canCheckPure":true,"children":[]}]},{"x":-61.96845667294616,"y":983.5418501836634,"rotation":0,"index":18,"name":"NewIceWaterBath","uuid":"05220051071689169","addedNode":[],"currentPlugCurValue":null,"currentContainer":null,"currentArea":null,"plugAnimation":false,"fun":false,"holdAnimation":false,"scaleX":1,"scaleY":1,"areaWasFullAry":[],"constructorAttribute":{"dataBuild":true},"medicineData":null,"bringToFront":true,"instanceName":"main.aid.NewIceWaterBath^1","dataVersion":7,"canCheckPure":true,"children":[]}],"capture":false,"moduleId":9}}