{"type":"sprite","x":0,"y":0,"name":"","0":{"x":-46.25,"y":-24.25,"name":"redPic","type":"sprite","r":0.8358472228751463,"sx":0.9970550537109375,"sy":0.9970550537109375,"a":0,"skewX":0.8358472228751463,"skewY":0.8358472228751463},"1":{"x":-29.6,"y":-4.1,"name":"refA","type":"sprite","r":0,"sx":0.997039794921875,"sy":0.997039794921875,"a":1,"skewX":0,"skewY":0,"napeData":{"linkage":"nape.Polygon.saveData","active":"true","allowDragging":"false","angularDamping":"0.0","angularVelocity":"0.0","applyGravity":"true","autoSleep":"true","awake":"true","bullet":"true","density":"1.0","disabled":"false","fixedRotation":"false","focusOn":"false","friction":"2","groupIndex":"0","inertiaScale":"1","isGround":"false","isSensor":"false","linearDamping":"0.0","linearVelocityX":"0.0","linearVelocityY":"0.0","reportBeginContact":"false","reportEndContact":"false","reportPostSolve":"false","reportPreSolve":"false","restitution":"0.2","tweened":"false","type":"Dynamic","collideGroup":["0"],"useParticleSystem":"false","particleRadius":"0.055","particleTexture":"","polyData":[[{"x":-51.08620758056641,"y":6.668029785156252},{"x":-37.426762390136716,"y":-22.99390411376953},{"x":8.736180114746098,"y":-7.29052734375},{"x":1.8566055297851562,"y":24.166078186035158}]]},"0":{"type":"shape","path":[255,28.35,31.55,2,10.8,-21.55,2,-18.95,-7.85,2,-3.2,38.45,2,28.35,31.55,2,28.35,31.55,1,1,3394611,1,32]}},"2":{"x":-58.5,"y":-22.1,"name":"blackPic","type":"sprite","r":0,"sx":0.997039794921875,"sy":0.997039794921875,"a":1,"skewX":0,"skewY":0,"0":{"type":"bitmap","libName":"燃烧前.png","x":6.75,"y":7.25,"r":0,"sx":0.29998779296875,"sy":0.29998779296875,"skewX":0,"skewY":0}}}